{
  "species": "cobblemon:rillaboom",
  "order": 3,
  "variations": [
    {
      "aspects": [
        "gmax"
      ],
      "poser": "mega_showdown:rillaboomgmax",
      "model": "mega_showdown:rillaboom_gigantamax.geo",
      "texture": "mega_showdown:textures/pokemon/0812_rillaboom/rillaboom_gigantamax.png",
      "layers": [
        {
          "name": "emissive",
          "texture": "mega_showdown:textures/pokemon/0812_rillaboom/rillaboom_gigantamax_emissive.png",
          "emissive": true
        }
      ]
    },
    {
      "aspects": [
        "shiny",
        "gmax"
      ],
      "texture": "mega_showdown:textures/pokemon/0812_rillaboom/rillaboom_gigantamax_shiny.png",
      "layers": [
      ]
    }
  ]
}
